{
  "name": "oh-my-posh",
  "source": "fig",
  "sourceUrl": "https://github.com/withfig/autocomplete/tree/master/src/oh-my-posh.ts",
  "description": "",
  "options": [
    {
      "name": [
        "--help",
        "-h"
      ],
      "description": "Show help for oh-my-posh"
    }
  ],
  "subcommands": [
    {
      "name": "init",
      "description": "Initialize oh-my-posh for your shell",
      "args": [
        {
          "name": "SHELL"
        }
      ],
      "options": [
        {
          "name": [
            "--config",
            "-c"
          ],
          "description": "The config file to use",
          "args": [
            {
              "name": "CONFIG",
              "description": "The configuration to use"
            }
          ]
        },
        {
          "name": [
            "--print",
            "-p"
          ],
          "description": "Print the init script"
        }
      ]
    },
    {
      "name": "get",
      "description": "Get oh-my-posh values",
      "args": [
        {
          "name": "VALUE"
        }
      ]
    },
    {
      "name": "debug",
      "description": "Debug oh-my-posh, example usage: 'oh-my-posh debug'",
      "options": [
        {
          "name": [
            "--config",
            "-c"
          ],
          "description": "The config file to use",
          "args": [
            {
              "name": "CONFIG",
              "description": "The configuration to use"
            }
          ]
        }
      ]
    },
    {
      "name": "config",
      "description": "Interact with the oh-my-posh configuration",
      "options": [
        {
          "name": [
            "--config",
            "-c"
          ],
          "description": "The config file to use",
          "args": [
            {
              "name": "CONFIG",
              "description": "The configuration to use"
            }
          ]
        }
      ],
      "subcommands": [
        {
          "name": "edit",
          "description": "Edit the config file, example usage: 'oh-my-posh config edit'"
        },
        {
          "name": "migrate",
          "description": "Migrate the config file, example usage: 'oh-my-posh config migrate --config ~/.config.omp.json'",
          "options": [
            {
              "name": [
                "--write",
                "-w"
              ],
              "description": "Write the migrated config to the configuration file, example usage: 'oh-my-posh config migrate --write'"
            },
            {
              "name": [
                "--format",
                "-f"
              ],
              "description": "The file format to use",
              "args": [
                {
                  "name": "FORMAT",
                  "description": "The export format"
                }
              ]
            }
          ]
        },
        {
          "name": "export",
          "description": "Export the config file, example usage: 'oh-my-posh config export --config ~/.config.omp.toml'",
          "options": [
            {
              "name": [
                "--output",
                "-o"
              ],
              "description": "The file to output the migrated config to, example usage: 'oh-my-posh config export --output ~/.config.omp.json'",
              "args": [
                {
                  "name": "OUTPUT",
                  "description": "The file to write to"
                }
              ]
            },
            {
              "name": [
                "--format",
                "-f"
              ],
              "description": "The file format to use",
              "args": [
                {
                  "name": "FORMAT",
                  "description": "The export format"
                }
              ]
            }
          ]
        }
      ]
    },
    {
      "name": "print",
      "description": "Print a prompt",
      "args": [
        {
          "name": "PROMPT"
        }
      ],
      "options": [
        {
          "name": [
            "--config",
            "-c"
          ],
          "description": "The config file to use",
          "args": [
            {
              "name": "CONFIG",
              "description": "The configuration to use"
            }
          ]
        },
        {
          "name": [
            "--terminal-width",
            "-w"
          ],
          "description": "The terminal width, example usage: 'oh-my-posh print primary --terminal-width 200'",
          "args": [
            {
              "name": "WIDTH",
              "description": "The terminal width"
            }
          ]
        },
        {
          "name": "--command",
          "description": "The current command for tooltips, example usage: 'oh-my-posh print tooltip --command az'",
          "args": [
            {
              "name": "COMMAND",
              "description": "The tooltip command"
            }
          ]
        },
        {
          "name": [
            "--error",
            "-e"
          ],
          "description": "The last exit code, example usage: 'oh-my-posh print primary --error 127'",
          "args": [
            {
              "name": "ERROR CODE",
              "description": "The last error code"
            }
          ]
        },
        {
          "name": "--eval",
          "description": "Use eval to render the prompt, example usage: 'oh-my-posh print primary --eval'"
        },
        {
          "name": "--execution-time",
          "description": "Use last command execution time in millis, example usage: 'oh-my-posh print primary --execution-time 200'",
          "args": [
            {
              "name": "EXECUTION TIME",
              "description": "The last command's execution time"
            }
          ]
        },
        {
          "name": [
            "--plain",
            "-p"
          ],
          "description": "Print a prompt without ASNI codes, example usage: 'oh-my-posh print primary --plain'"
        },
        {
          "name": "--pswd",
          "description": "The current working directory according to PowerShell, example usage: 'oh-my-posh print primary --pswd C:\\Users\\user\\Documents'",
          "args": [
            {
              "name": "POWERSHELL WORKING DIRECTORY",
              "description": "The working directory according to PowerShell"
            }
          ]
        },
        {
          "name": "--pwd",
          "description": "The current working directory, example usage: 'oh-my-posh print primary --pwd /home/user/Documents'",
          "args": [
            {
              "name": "WORKING DIRECTORY",
              "description": "The working directory"
            }
          ]
        },
        {
          "name": "--shell",
          "description": "The current shell, example usage: 'oh-my-posh print primary --shell fish'",
          "args": [
            {
              "name": "SHELL",
              "description": "The shell used"
            }
          ]
        },
        {
          "name": "--stack-count",
          "description": "The directory stack count, example usage: 'oh-my-posh print primary --stack-count 1'",
          "args": [
            {
              "name": "NUM",
              "description": "The number of stacks"
            }
          ]
        }
      ]
    },
    {
      "name": "version",
      "description": "Display the oh-my-posh version, example usage: 'oh-my-posh version'"
    }
  ]
}
